mcp_cli/colors.py
mcp_cli/config.py
mcp_cli/connection.py
mcp_cli/console.py
mcp_cli/exceptions.py
mcp_cli/logging_utils.py
mcp_cli/main.py
mcp_cli/types.py
mcp_cli/utils.py
mcp_cli/auth/config.py
mcp_cli/auth/discovery.py
mcp_cli/auth/oauth_manager.py
mcp_cli/auth/utils.py
mcp_cli/commands/__init__.py
mcp_cli/commands/auth.py
mcp_cli/commands/servers.py
mcp_cli/commands/tools.py
devin_mcp_cli-0.1.15.dist-info/METADATA
devin_mcp_cli-0.1.15.dist-info/WHEEL
devin_mcp_cli-0.1.15.dist-info/entry_points.txt
devin_mcp_cli-0.1.15.dist-info/top_level.txt
devin_mcp_cli-0.1.15.dist-info/RECORD
