Metadata-Version: 2.4
Name: devin-mcp-cli
Version: 0.1.15
Summary: A CLI for MCP
Author-email: Your Name <fede@cognition.ai>
Keywords: cli,mcp
Requires-Python: >=3.11
Requires-Dist: typer>=0.15.2
Requires-Dist: rich>=13.9.4
Requires-Dist: python-dotenv>=1.1.0
Requires-Dist: asyncio>=3.4.3
Requires-Dist: mcp>=1.6.0
Requires-Dist: httpx-auth>=0.22.0
Provides-Extra: wasm
